{"schedule":[{"type":"HF","style":"Vorlesung Fixzeit","room":"virt_mkilian","comment":"(Produktentwicklung MB+MB int + Fallstudien WT 4) - Online Angebot in Moodle -","startdate":"20.04.2020","day":"Montag","endtime":"13:00","group":"","label":"Fallstudien und Planspiele","starttime":"11:30","docent":"Prof. Dr. Matthias Kilian","enddate":"14.12.2020","splusname":"X_FPS#PMuPE§mkilian_2%64676\/64719 $ 2","sp":"-","id":"3615380"},{"type":"HF","style":"Vorlesung Fixzeit","room":"virt_mblank","startdate":"21.04.2020","comment":"- Glas - (Wing WT 4 + WT 4) - Online Angebot in Moodle -","day":"Dienstag","group":"","endtime":"09:30","label":"Glas \/ Keramik","starttime":"08:00","docent":"Prof. Dr. Margarete Blank-Bewersdorff","enddate":"15.12.2020","splusname":"GK§mblank_2%64647 $ 2","sp":"-","id":"3616542"},{"type":"HF","style":"Vorlesung Fixzeit","day":"Dienstag","comment":"- Online Angebot in Moodle -","room":"virt_rhechtfi","startdate":"21.04.2020","endtime":"11:15","group":"","label":"Verkaufskommunikation","starttime":"09:45","docent":"Prof. Dr. Ronald Hechtfischer","enddate":"15.12.2020","splusname":"VKKom§rhechtfi_3%64675 $ 2","sp":"-","id":"3615569"},{"type":"HF","style":"Vorlesung Fixzeit","room":"virt_rhechtfi","day":"Dienstag","comment":"- Online Angebot in Moodle -","startdate":"21.04.2020","endtime":"13:00","group":"","label":"Verkaufskommunikation","starttime":"11:30","docent":"Prof. Dr. Ronald Hechtfischer","enddate":"15.12.2020","splusname":"VKKom§rhechtfi_3%64674 $ 2","sp":"-","id":"3615570"},{"type":"HF","style":"Praktikum Fixzeit","room":"virt_jrubitz","day":"Dienstag","startdate":"21.04.2020","comment":"- elektrische Messtechnik - (Termine nach der 1. Vorlesung nach Plan)","group":"","endtime":"15:30","label":"Messtechnik","starttime":"14:00","docent":"Dipl.-Ing. Jürgen Rubitzko","enddate":"15.12.2020","splusname":"Mte§jrubitz_1%64682 $ 2","sp":"-","id":"3616187"},{"type":"HF","style":"Praktikum Fixzeit","day":"Dienstag","comment":"- Praktikum - (WT4) (Termine nach der 1. Vorlesung nach Plan)","room":"virt_mlinss","startdate":"28.04.2020","group":"","endtime":"15:30","label":"Messtechnik","starttime":"14:00","docent":"Prof. Dr. Marco Linß","enddate":"15.12.2020","splusname":"Mte§mlinss_2%64680 $ 2","sp":"-","id":"3616184"},{"type":"HF","style":"Praktikum Fixzeit","day":"Dienstag","startdate":"21.04.2020","comment":"- Grundbildung Messtechnik - (Termine nach der 1. Vorlesung nach Plan)","room":"virt_rmartin","endtime":"15:30","group":"","label":"Messtechnik","starttime":"14:00","docent":" Roland Martin","enddate":"15.12.2020","splusname":"Mte§rmartin_1%64683 $ 2","sp":"-","id":"3616173"},{"type":"HF","style":"Vorlesung Fixzeit","day":"Mittwoch","comment":"- Keramik - (Wing WT 4 + WT 4) - Online Angebot in moodle -","room":"virt_hschmidt","startdate":"22.04.2020","group":"","endtime":"09:30","label":"Glas \/ Keramik","starttime":"08:00","docent":"Prof. Dr. Hans Schmidt","enddate":"16.12.2020","splusname":"GK§hschmidt_2%64648 $ 2","sp":"-","id":"3616543"},{"type":"HF","style":"Vorlesung Fixzeit","room":"virt_hschmidt","comment":"(Wing WT + WT 4) - Vorlesunge - (die Praktikumstermine werden noch bekannt gegeben) -- Online Angebot in moodle -","startdate":"22.04.2020","day":"Mittwoch","endtime":"13:00","group":"","label":"Kunststoffe","starttime":"11:30","docent":"Prof. Dr. Hans Schmidt","enddate":"16.12.2020","splusname":"Ku§hschmidt_2%64689 $ 2","sp":"-","id":"3616281"},{"type":"HF","style":"Praktikum Fixzeit","room":"virt_jbeck","startdate":"29.04.2020","comment":"- Praktikum - (ab KW 18)","day":"Mittwoch","endtime":"15:30","group":"","label":"Fallstudien und Planspiele","starttime":"14:00","docent":"Prof. Dr. Jens Beck","enddate":"16.12.2020","splusname":"X_FPS#PMuPE§jbeck%64677 $ 2","sp":"-","id":"3615382"},{"type":"HF","style":"Vorlesung Fixzeit","room":"virt_mlinss","startdate":"23.04.2020","comment":"(MB + MB Int + WT 4 + UT 6 FWPM) - Online Angebot in Moodle -","day":"Donnerstag","group":"","endtime":"11:15","label":"Messtechnik","starttime":"09:45","docent":"Prof. Dr. Marco Linß","enddate":"17.12.2020","splusname":"Mte§mlinss_2%64694\/64679\/64900 $ 2","sp":"-","id":"3616181"},{"type":"HF","style":"Übungen Fixzeit","day":"Donnerstag","room":"virt_mlinss","comment":"- Übungen - (14-tägig) (Beginn KW 17) (MB + MB Int + WT 4 + UT 6 FWPM)","startdate":"23.04.2020","group":"","endtime":"13:00","label":"Messtechnik","starttime":"11:30","docent":"Prof. Dr. Marco Linß","enddate":"17.12.2020","splusname":"Mte§mlinss_2%64698\/64681\/64902 $ 2","sp":"-","id":"3616175"},{"type":"HF","style":"Vorlesung Fixzeit","day":"Donnerstag","comment":"(Wing WT + WT 4) - Online Angebot in Moodle -","startdate":"23.04.2020","room":"virt_mgory","endtime":"15:30","group":"","label":"Werkstofftechnik metallischer Werkstoffe","starttime":"14:00","docent":"Prof. Dr. Marek Gorywoda","enddate":"17.12.2020","splusname":"WmW§mgory_2%64645 $ 2","sp":"-","id":"3615473"},{"type":"HF","style":"Vorlesung Fixzeit","day":"Donnerstag","room":"virt_mgory","comment":"(Wing WT + WT 4) - Online Angebot in Moodle -","startdate":"23.04.2020","group":"","endtime":"17:15","label":"Werkstofftechnik metallischer Werkstoffe","starttime":"15:45","docent":"Prof. Dr. Marek Gorywoda","enddate":"17.12.2020","splusname":"WmW§mgory_2%64646 $ 2","sp":"-","id":"3615471"},{"type":"HF","style":"Vorlesung Fixzeit","day":"Freitag","startdate":"24.04.2020","comment":"(Wing WT + WT 4) - Vorlesunge - (die Praktikumstermine werden noch bekannt gegeben) - Online Angebot in moodle -","room":"virt_hschmidt","endtime":"09:30","group":"","label":"Kunststoffe","starttime":"08:00","docent":"Prof. Dr. Hans Schmidt","enddate":"18.12.2020","splusname":"Ku§hschmidt_2%64688 $ 2","sp":"-","id":"3616284"}],"version":3.5}