{"schedule":[{"type":"HF","comment":"(MB + MB int + ET 1)","sp":"-","startdate":"02.03.2020","label":"Analysis","style":"Vorlesung Fixzeit","group":"","day":"Montag","splusname":"Ana§rhonke_2%66644 $ 2","enddate":"18.01.2021","room":"FA205\/206","id":"3855160","endtime":"09:30","docent":"Prof. Dr. Robert Honke","starttime":"08:00"},{"type":"HF","comment":"(MB + WT 1)","sp":"-","label":"Programmieren für Ingenieure","startdate":"02.03.2020","style":"Vorlesung Fixzeit","splusname":"Ping§fwagen_2%66651\/66604 $ 2","group":"","day":"Montag","enddate":"18.01.2021","room":"FB109","id":"3856530","endtime":"11:15","docent":"Dipl-Wirtschaftsinf. Frank Wagenknecht","starttime":"09:45"},{"type":"HF","comment":"- Übungen - (ab KW 42)","sp":"-","startdate":"02.03.2020","label":"Grundlagen der Elektrotechnik","style":"Übungen Fixzeit","group":"(Gruppe I)","day":"Montag","splusname":"GdET§wrichter_2%66657 $ 2","enddate":"18.01.2021","room":"FB110","id":"3855808","endtime":"13:00","docent":"Prof. Dr. Wolfgang Richter","starttime":"11:30"},{"type":"HF","comment":"(MB + WT 1)","sp":"-","label":"Grundlagen der Informationstechnik","startdate":"02.03.2020","style":"Vorlesung Fixzeit","day":"Montag","group":"","splusname":"GdInfT§jkrum_2%66648\/66595 $ 2","enddate":"18.01.2021","room":"FB109","id":"3855829","endtime":"15:30","docent":"Prof. Dr. Jörg Krumeich","starttime":"14:00"},{"type":"Tut","comment":"- Tutorium -  (MB+MB int+WT 1) (ab KW 43)","sp":"-","startdate":"02.03.2020","label":"Statik und Festigkeitslehre","style":"Tutorium Fixzeit","day":"Montag","splusname":"SuFTut§noell%68840 $ 2","group":"","enddate":"18.01.2021","room":"FB109","id":"3857718","endtime":"19:00","docent":" Loen Müller-Noell","starttime":"17:30"},{"type":"HF","comment":"(MB + WT 1)","sp":"-","startdate":"03.03.2020","label":"Programmieren für Ingenieure","style":"Vorlesung Fixzeit","day":"Dienstag","splusname":"Ping§fwagen_2%66652\/66605 $ 2","group":"","enddate":"19.01.2021","room":"FB007\/009","id":"3856532","endtime":"09:30","docent":"Dipl-Wirtschaftsinf. Frank Wagenknecht","starttime":"08:00"},{"type":"HF","comment":"(MB + MB int + ET 1)","sp":"-","label":"Analysis","startdate":"03.03.2020","style":"Vorlesung Fixzeit","splusname":"Ana§rhonke_2%66643 $ 2","day":"Dienstag","group":"","enddate":"19.01.2021","room":"FB109","id":"3855158","endtime":"11:15","docent":"Prof. Dr. Robert Honke","starttime":"09:45"},{"type":"HF","comment":"- Übungen - (Gruppe II mt MB int 1) (ab KW 42)","sp":"-","label":"Grundlagen der Elektrotechnik","startdate":"03.03.2020","style":"Übungen Fixzeit","splusname":"GdET§wrichter_2%66658\/68594 $ 2","group":"","day":"Dienstag","enddate":"19.01.2021","room":"FB110","id":"3856183","endtime":"13:00","docent":"Prof. Dr. Wolfgang Richter","starttime":"11:30"},{"type":"HF","comment":"(MB + MB int + WT 1)","sp":"-","startdate":"03.03.2020","label":"Statik und Festigkeitslehre","style":"Vorlesung Fixzeit","splusname":"SuF§tkarall_2%66593\/66687\/66645 $ 2","group":"","day":"Dienstag","enddate":"19.01.2021","room":"FA205\/206","id":"3856869","endtime":"15:30","docent":"Prof. Dr. Thomas Karall","starttime":"14:00"},{"type":"HF","comment":"- Übungen - online (ab KW 42)","sp":"-","label":"Programmieren für Ingenieure","startdate":"03.03.2020","style":"Übungen Fixzeit","day":"Dienstag","splusname":"Ping§fwagen_2%66653 $ 2","group":"(Gruppe I)","enddate":"19.01.2021","room":"FB110","id":"3856533","endtime":"17:15","docent":"Dipl-Wirtschaftsinf. Frank Wagenknecht","starttime":"15:45"},{"type":"HF","comment":"- Übungen - (MB Gr. II + MB int 1) (ab KW 41)","sp":"-","startdate":"04.03.2020","label":"Statik und Festigkeitslehre","style":"Übungen Fixzeit","day":"Mittwoch","group":"","splusname":"SuF§astein_1%66647\/67360 $ 2","enddate":"20.01.2021","room":"FB109","id":"3855366","endtime":"09:30","docent":"Dipl.-Ing. Andreas Stein","starttime":"08:00"},{"type":"HF","comment":"- Übungen - (ab KW 41)","sp":"-","label":"Statik und Festigkeitslehre","startdate":"04.03.2020","style":"Übungen Fixzeit","splusname":"SuF§tkarall_2%66646 $ 2","group":"(Gruppe I)","day":"Mittwoch","enddate":"20.01.2021","room":"FA202","id":"3856872","endtime":"11:15","docent":"Prof. Dr. Thomas Karall","starttime":"09:45"},{"type":"HF","comment":"(MB + MB int + WT + Wing 1 + ET 3)","sp":"-","label":"Betriebswirtschaftliche Grundlagen für Ingenieure","startdate":"04.03.2020","style":"Vorlesung Fixzeit","day":"Mittwoch","splusname":"BWLIng§cfalken_2%66587 $ 2","group":"","enddate":"20.01.2021","room":"FG023a\/023b","id":"3855333","endtime":"13:00","docent":"Prof. Dr. Christine Falkenreck","starttime":"11:30"},{"type":"HF","comment":"- Übungen - (ab KW 42)  (MB Gr. I + WT)","sp":"-","startdate":"04.03.2020","label":"Grundlagen der Informationstechnik","style":"Übungen Fixzeit","splusname":"GdInfT§jrubitz_1%66596\/66649 $ 2","day":"Mittwoch","group":"","enddate":"20.01.2021","room":"FA012","id":"3857693","endtime":"15:30","docent":"Dipl.-Ing. Jürgen Rubitzko","starttime":"14:00"},{"type":"HF","comment":"- Übungen - (ab KW 41)","sp":"-","label":"Grundlagen der Informationstechnik","startdate":"05.03.2020","style":"Übungen Fixzeit","splusname":"GdInfT§jrubitz_1%66650 $ 2","day":"Donnerstag","group":"(Gruppe II)","enddate":"21.01.2021","room":"FA012","id":"3855831","endtime":"09:30","docent":"Dipl.-Ing. Jürgen Rubitzko","starttime":"08:00"},{"type":"HF","comment":"(MB + MB int + WT + Wing 1 + ET 3) (ab KW 41)","sp":"-","label":"Betriebswirtschaftliche Grundlagen für Ingenieure","startdate":"05.03.2020","style":"Vorlesung Fixzeit","day":"Donnerstag","splusname":"BWLIng§cfalken_2%66588 $ 2","group":"","enddate":"21.01.2021","room":"FG023a\/023b","id":"3855336","endtime":"11:15","docent":"Prof. Dr. Christine Falkenreck","starttime":"09:45"},{"type":"HF","comment":"(MB + MB int 1 + Wing PP 5 FWPM) (ab KW 41)","sp":"-","startdate":"05.03.2020","label":"Grundlagen der Elektrotechnik","style":"Vorlesung Fixzeit","splusname":"GdET§wrichter_2%66656\/68069\/68593 $ 2","day":"Donnerstag","group":"","enddate":"21.01.2021","room":"FB109","id":"3856179","endtime":"13:00","docent":"Prof. Dr. Wolfgang Richter","starttime":"11:30"},{"type":"HF","comment":"- Übungen onlie - (ab KW 42)","sp":"-","startdate":"05.03.2020","label":"Programmieren für Ingenieure","style":"Übungen Fixzeit","group":"(Gruppe II)","splusname":"Ping§fwagen_2%66654 $ 2","day":"Donnerstag","enddate":"21.01.2021","room":"FB110","id":"3856534","endtime":"15:30","docent":"Dipl-Wirtschaftsinf. Frank Wagenknecht","starttime":"14:00"},{"type":"HF","comment":"- Zusatzübungen online - (ab KW 43)","sp":"-","startdate":"05.03.2020","label":"Programmieren für Ingenieure","style":"Tutorium Fixzeit","group":"","splusname":"Ping§fwagen_2%67426 $ 2","day":"Donnerstag","enddate":"21.01.2021","room":"FB110","id":"3856535","endtime":"17:15","docent":"Dipl-Wirtschaftsinf. Frank Wagenknecht","starttime":"15:45"},{"type":"Tut","comment":"- Tutorium -","sp":"-","label":"Vektorrechnung","startdate":"06.11.2020","style":"Blockveranstaltung","group":"","day":"Freitag","splusname":"VekR§jbeck%70430 $ 2","enddate":"06.11.2020","room":"virt_jbeck","id":"3858173","endtime":"19:00","docent":"Prof. Dr. Jens Beck","starttime":"14:00"}],"version":3.5}