{"schedule":[{"room":"FB109","startdate":"08.03.2021","endtime":"16:30","day":"Montag","id":"3856482","style":"Praktikumsblock","group":"(Gruppe II)","type":"HF","label":"Praxisblock I","docent":"Prof. Dr. Jürgen Heym","sp":"-","starttime":"08:30","comment":"- \"Rechnernetze Praxis\" -","splusname":"PB1§jheym_2%67198 $ 2","enddate":"08.03.2021"},{"room":"FB006","startdate":"08.03.2021","endtime":"17:00","day":"Montag","id":"3856473","group":"(Gruppe I)","style":"Praktikumsblock","type":"HF","label":"Praxisblock I","docent":"Prof. Dr. Günther Köhler","sp":"-","starttime":"09:00","comment":"- \"Unix\" -","splusname":"PB1§gkoehler_2%67193 $ 2","enddate":"08.03.2021"},{"room":"FB004A","startdate":"08.03.2021","endtime":"17:00","day":"Montag","id":"3856463","group":"(Gruppe III)","style":"Praktikumsblock","type":"HF","label":"Praxisblock I","docent":"Prof. Dr. Florian Adamsky","sp":"-","starttime":"09:00","comment":"- \"IT-Sicherheit\"","splusname":"PB1§fadam%67203 $ 2","enddate":"08.03.2021"},{"room":"FB006","startdate":"09.03.2021","endtime":"16:00","day":"Dienstag","id":"3856475","style":"Praktikumsblock","group":"(Gruppe I)","type":"HF","label":"Praxisblock I","docent":"Prof. Dr. Günther Köhler","sp":"-","starttime":"08:00","comment":"- \"Unix\" -","splusname":"PB1§gkoehler_2%67194 $ 2","enddate":"09.03.2021"},{"room":"FB109","startdate":"09.03.2021","endtime":"16:30","day":"Dienstag","id":"3856485","group":"(Gruppe II)","style":"Praktikumsblock","type":"HF","label":"Praxisblock I","docent":"Prof. Dr. Jürgen Heym","sp":"-","starttime":"08:30","comment":"- \"Rechnernetze Praxis\" -","splusname":"PB1§jheym_2%67199 $ 2","enddate":"09.03.2021"},{"room":"FB004A","startdate":"09.03.2021","endtime":"17:00","day":"Dienstag","id":"3856464","style":"Praktikumsblock","group":"(Gruppe III)","type":"HF","label":"Praxisblock I","docent":"Prof. Dr. Florian Adamsky","sp":"-","starttime":"09:00","comment":"- \"IT-Sicherheit\"","splusname":"PB1§fadam%67204 $ 2","enddate":"09.03.2021"},{"room":"FB006","startdate":"10.03.2021","endtime":"16:00","day":"Mittwoch","id":"3856476","style":"Praktikumsblock","group":"(Gruppe I)","type":"HF","label":"Praxisblock I","docent":"Prof. Dr. Günther Köhler","sp":"-","starttime":"08:00","comment":"- \"Unix\" -","splusname":"PB1§gkoehler_2%67195 $ 2","enddate":"10.03.2021"},{"starttime":"08:30","style":"Praktikumsblock","label":"Praxisblock I","startdate":"10.03.2021","group":"(Gruppe II)","enddate":"10.03.2021","type":"HF","splusname":"PB1§jheym_2%67200 $ 2","endtime":"16:30","docent":"Prof. Dr. Jürgen Heym","room":"FB109","comment":"- \"Rechnernetze Praxis\" -","id":"3856487","sp":"-","day":"Mittwoch"},{"style":"Praktikumsblock","starttime":"09:00","startdate":"10.03.2021","label":"Praxisblock I","group":"(Gruppe III)","enddate":"10.03.2021","type":"HF","splusname":"PB1§fadam%67205 $ 2","endtime":"17:00","docent":"Prof. Dr. Florian Adamsky","room":"FB004A","comment":"- \"IT-Sicherheit\"","id":"3856466","sp":"-","day":"Mittwoch"},{"starttime":"08:00","style":"Praktikumsblock","label":"Praxisblock I","startdate":"11.03.2021","group":"(Gruppe I)","enddate":"11.03.2021","type":"HF","splusname":"PB1§gkoehler_2%67196 $ 2","endtime":"16:00","docent":"Prof. Dr. Günther Köhler","room":"FB006","comment":"- \"Unix\" -","id":"3856479","sp":"-","day":"Donnerstag"},{"style":"Praktikumsblock","starttime":"08:30","startdate":"11.03.2021","label":"Praxisblock I","group":"(Gruppe II)","enddate":"11.03.2021","type":"HF","splusname":"PB1§jheym_2%67201 $ 2","endtime":"16:30","docent":"Prof. Dr. Jürgen Heym","room":"FB109","comment":"- \"Rechnernetze Praxis\" -","id":"3856488","sp":"-","day":"Donnerstag"},{"starttime":"09:00","style":"Praktikumsblock","startdate":"11.03.2021","label":"Praxisblock I","group":"(Gruppe III)","enddate":"11.03.2021","type":"HF","splusname":"PB1§fadam%67206 $ 2","endtime":"17:00","docent":"Prof. Dr. Florian Adamsky","room":"FB004A","comment":"- \"IT-Sicherheit\"","id":"3856468","sp":"-","day":"Donnerstag"},{"style":"Praktikumsblock","starttime":"08:00","startdate":"12.03.2021","label":"Praxisblock I","group":"(Gruppe I)","enddate":"12.03.2021","type":"HF","splusname":"PB1§gkoehler_2%67197 $ 2","endtime":"12:00","docent":"Prof. Dr. Günther Köhler","room":"FB006","comment":"- \"Unix\" -","id":"3856481","sp":"-","day":"Freitag"},{"starttime":"08:30","splusname":"PB1§jheym_2%67202 $ 2","enddate":"12.03.2021","group":"(Gruppe II)","startdate":"12.03.2021","room":"FB109","docent":"Prof. Dr. Jürgen Heym","id":"3856491","day":"Freitag","comment":"- \"Rechnernetze Praxis\" -","style":"Praktikumsblock","sp":"-","endtime":"12:30","type":"HF","label":"Praxisblock I"},{"starttime":"09:00","day":"Freitag","enddate":"12.03.2021","group":"(Gruppe III)","startdate":"12.03.2021","room":"FB004A","docent":"Prof. Dr. Florian Adamsky","comment":"- \"IT-Sicherheit\"","id":"3856470","splusname":"PB1§fadam%67209 $ 2","style":"Praktikumsblock","sp":"-","endtime":"13:00","label":"Praxisblock I","type":"HF"}],"version":3.5}